odoo/addons/mrp_bom_product_price_margin/README.rst
odoo/addons/mrp_bom_product_price_margin/__init__.py
odoo/addons/mrp_bom_product_price_margin/__manifest__.py
odoo/addons/mrp_bom_product_price_margin/i18n/fr.po
odoo/addons/mrp_bom_product_price_margin/i18n/it.po
odoo/addons/mrp_bom_product_price_margin/i18n/mrp_bom_product_price_margin.pot
odoo/addons/mrp_bom_product_price_margin/models/__init__.py
odoo/addons/mrp_bom_product_price_margin/models/mrp_bom.py
odoo/addons/mrp_bom_product_price_margin/models/mrp_bom_line.py
odoo/addons/mrp_bom_product_price_margin/models/product_template.py
odoo/addons/mrp_bom_product_price_margin/readme/CONTRIBUTORS.rst
odoo/addons/mrp_bom_product_price_margin/readme/DESCRIPTION.rst
odoo/addons/mrp_bom_product_price_margin/readme/USAGE.rst
odoo/addons/mrp_bom_product_price_margin/static/mrp_bom_product_price_margin_diff.jpeg
odoo/addons/mrp_bom_product_price_margin/static/mrp_bom_product_price_margin_no_diff.jpeg
odoo/addons/mrp_bom_product_price_margin/static/mrp_bom_product_price_margin_tree.png
odoo/addons/mrp_bom_product_price_margin/static/description/icon.png
odoo/addons/mrp_bom_product_price_margin/static/description/index.html
odoo/addons/mrp_bom_product_price_margin/tests/__init__.py
odoo/addons/mrp_bom_product_price_margin/tests/test_mrp_bom_sale_margin.py
odoo/addons/mrp_bom_product_price_margin/views/view_mrp_bom.xml
odoo_addon_mrp_bom_product_price_margin-16.0.1.1.0.dist-info/METADATA
odoo_addon_mrp_bom_product_price_margin-16.0.1.1.0.dist-info/WHEEL
odoo_addon_mrp_bom_product_price_margin-16.0.1.1.0.dist-info/top_level.txt
odoo_addon_mrp_bom_product_price_margin-16.0.1.1.0.dist-info/RECORD
