Metadata-Version: 2.1
Name: odoo-addon-mrp_bom_product_price_margin
Version: 16.0.1.1.0
Summary: Handle Product Standard, Sale Price and Margin with its BoM cost
Home-page: https://github.com/OCA/manufacture
Author: GRAP, Odoo Community Association (OCA)
Author-email: support@odoo-community.org
License: AGPL-3
Classifier: Programming Language :: Python
Classifier: Framework :: Odoo
Classifier: Framework :: Odoo :: 16.0
Classifier: License :: OSI Approved :: GNU Affero General Public License v3
Requires-Python: >=3.10
Requires-Dist: odoo-addon-product-standard-margin<16.1dev,>=16.0dev
Requires-Dist: odoo<16.1dev,>=16.0a
